<?xml version='1.0' encoding='UTF-8'?>
<MEDDOCAN>
  <TEXT>
    Datos del paciente.
    Nombre: <TAG TYPE="NOMBRE_SUJETO_ASISTENCIA">Celia</TAG> <TAG TYPE="NOMBRE_SUJETO_ASISTENCIA">Jiménez Roca</TAG>.
    DNI: <TAG TYPE="ID_SUJETO_ASISTENCIA">30923770V</TAG>.
    Fecha de nacimiento: <TAG TYPE="FECHAS">27/11/1989</TAG>.
    Género: <TAG TYPE="SEXO_SUJETO_ASISTENCIA">F</TAG>.
    Domicilio: <TAG TYPE="CALLE">Calle de Velázquez 79, 2Z</TAG>.
    Ciudad: <TAG TYPE="TERRITORIO">Langreo, Toledo, Castilla-La Mancha</TAG>.
    Código postal: <TAG TYPE="TERRITORIO">45208</TAG>.
    Email: <TAG TYPE="CORREO_ELECTRONICO">celiaroca@ciberer.es</TAG>.
    Teléfono fijo: <TAG TYPE="NUMERO_TELEFONO">+34 925 87 77 57</TAG>.
    Teléfono móvil: <TAG TYPE="NUMERO_TELEFONO">+34 625 20 54 89</TAG>.
    NHC: <TAG TYPE="ID_SUJETO_ASISTENCIA">8817113</TAG>.
    NASS: <TAG TYPE="ID_ASEGURAMIENTO">575585124311</TAG>.
    Condición de riesgo: <TAG TYPE="OTROS_SUJETO_ASISTENCIA">Trabajador de Minería</TAG>.
    Datos asistenciales.
    Médico: <TAG TYPE="NOMBRE_PERSONAL_SANITARIO">Dra. Sonia</TAG> <TAG TYPE="NOMBRE_PERSONAL_SANITARIO">Conde Izquierdo</TAG>. NC <TAG TYPE="ID_TITULACION_PERSONAL_SANITARIO">914486925</TAG>. <TAG TYPE="PROFESION">Oftalmóloga Especialista en Retina y Vítreo</TAG>. <TAG TYPE="INSTITUCION">Instituto Universitario de Oftalmobiología Aplicada (IOBA)</TAG>. <TAG TYPE="CALLE">Avenida Ramón y Cajal, 7</TAG>. <TAG TYPE="TERRITORIO">47011</TAG>. <TAG TYPE="TERRITORIO">Valladolid</TAG>. <TAG TYPE="PAIS">España</TAG>.
    Fecha de ingreso: <TAG TYPE="FECHAS">25/08/2008</TAG>.
    Episodio: <TAG TYPE="ID_CONTACTO_ASISTENCIAL">48852206</TAG>.
    Centro de salud: <TAG TYPE="CENTRO_SALUD">Centro de Salud Conde de Casal</TAG>.
    Informe clínico del paciente:
    Paciente de <TAG TYPE="OTROS_SUJETO_ASISTENCIA">ascendencia centroasiática</TAG> de <TAG TYPE="EDAD_SUJETO_ASISTENCIA">18 años</TAG> de edad, acompañado de su suegra. Presenta un cuadro de visión borrosa en el ojo derecho desde hace 3 días, con fotofobia y dolor ocular. La exploración física revela: Tª <TAG TYPE="FECHAS">37,5 C</TAG>; T.A: <TAG TYPE="FECHAS">120/80 mmHg</TAG>; Fc: <TAG TYPE="FECHAS">90 lpm</TAG>. Se encuentra consciente, orientado, sin sudoración ni signos de infección. En la exploración oftalmológica se aprecia una úlcera corneal en el ojo derecho, con descarga purulenta y edema conjuntival.
    Los datos analíticos muestran los siguientes resultados: Hemograma: Hb <TAG TYPE="FECHAS">13,5 g/dl</TAG>; leucocitos <TAG TYPE="FECHAS">8.500/mm3</TAG> (neutrófilos 50%); plaquetas <TAG TYPE="FECHAS">200.000/ mm3</TAG>. Orina: sedimento normal.
    Se solicitan pruebas de imagen (Ecografía ocular y Tomografía computarizada de la cabeza) que no evidencian patología significativa. Con el diagnóstico de úlcera corneal se instaura tratamiento sintomático (antitérmicos, antiinflamatorios, reposo y elevación ocular) así como tratamiento antibiótico específico: <TAG TYPE="MEDICAMENTO">Cefalexina 500 mg</TAG> vía oral cada 6 horas (durante 7 días). El paciente mejora significativamente de su cuadro tras 3 días de tratamiento, decidiéndose el alta a su domicilio donde completó la pauta de tratamiento antibiótico.
    Antecedentes:
    La paciente tiene antecedentes de <TAG TYPE="OTROS_SUJETO_ASISTENCIA">alergia a penicilina</TAG>.
    Evolución y comentarios:
    El paciente se mantiene estable y sin complicaciones durante el período de alta.
    Remitido por:
    Se remitió al paciente a su domicilio con instrucciones de seguimiento en el Servicio de Oftalmología del Centro de Salud Conde de Casal.
  </TEXT>
</MEDDOCAN>